{
    "lang": "id",
    "goBackUp": "Kembali ke atas",
    "report": "Kirim laporan",
    "contactDialogTitle": "Formulir Kontak",
    "contactDialogDescription": "Silakan isi formulir dan pilih topik dukungan untuk membantu Anda lebih baik.",
    "contactDialogName": "Nama",
    "contactDialogNameDescription": "Silakan masukkan nama lengkap Anda.",
    "contactDialogSupportOptionsLabel": "Pilih topik dukungan",
    "contactDialogEmailLabel": "Email",
    "contactDialogEmailDescription": "Masukkan email yang valid untuk menerima balasan.",
    "contactDialogMessageLabel": "Pesan",
    "contactDialogMessageDescription": "Tulis pesan Anda di sini.",
    "contactDialogCaptchaLabel": "Selesaikan captcha",
    "contactDialogCaptchaQuestion": "Apa pertanyaan captcha?",
    "contactDialogCaptchaDescription": "Jawab pertanyaan captcha untuk mengirimkan formulir.",
    "contactDialogCaptchaPlaceholder": "Jawaban",
    "contactDialogSuccess": "Pesan berhasil dikirim.",
    "contactDialogError": "Kesalahan dalam menyelesaikan captcha.",
    "contactDialogSubmitButtonText": "Kirim",
    "contactDialogSubmitButtonAriaLabel": "Kirim formulir kontak",
    "contactDialogCloseButtonText": "Tutup",
    "contactDialogCloseButtonAriaLabel": "Tutup formulir kontak",
    "SupportOptionsNull": "Pilih opsi...",
    "SupportOptionsSuggestions": "Saran dan Keluhan",
    "SupportOptionsTranslationErrors": "Kesalahan Terjemahan",
    "SupportOptionsRecordingIssues": "Masalah Perekaman",
    "SupportOptionsQualityIssues": "Kualitas Video atau Audio",
    "SupportOptionsBrowserCompatibility": "Kesalahan Kompatibilitas Browser",
    "SupportOptionsDeviceSetup": "Pengaturan Perangkat",
    "SupportOptionsLagFreezing": "Keterlambatan atau Pembekuan",
    "SupportOptionsDeviceAccess": "Akses Ditolak ke Perangkat",
    "SupportOptionsFeatureRequest": "Permintaan Fitur Baru",
    "SupportOptionsPrivacySecurity": "Pertanyaan tentang Privasi dan Keamanan",
    "SupportOptionsGeneralErrors": "Kesalahan Umum atau Kegagalan Teknis",
    "terms": "Syarat & Ketentuan",
    "privacy": "Privasi",
    "cookiesPolicy": "Kebijakan Cookie",
    "legal": "Ketentuan Hukum",
    "faq": "FAQ",
    "copyEmailTitle": "Salin email",
    "copyright": "Sebuah proyek dari <a href='https:\/\/itechware.com' target='_blank'>iTechWare<\/a> | Hak cipta dilindungi... dan kucing-kucing saya mengawasi."
}