{
    "lang": "te",
    "goBackUp": "పైకి వెళ్ళు",
    "report": "రిపోర్ట్ పంపండి",
    "contactDialogTitle": "సంప్రదింపు ఫారమ్",
    "contactDialogDescription": "దయచేసి ఫారమ్‌ను పూర్తి చేయండి మరియు మీకు మెరుగైన సహాయం చేయడానికి ఒక సపోర్ట్ థీమ్‌ను ఎంచుకోండి.",
    "contactDialogName": "పేరు",
    "contactDialogNameDescription": "దయచేసి మీ పూర్తి పేరును నమోదు చేయండి.",
    "contactDialogSupportOptionsLabel": "సపోర్ట్ థీమ్‌ను ఎంచుకోండి",
    "contactDialogEmailLabel": "ఇమెయిల్",
    "contactDialogEmailDescription": "ప్రతిస్పందనను స్వీకరించడానికి చెల్లుబాటు అయ్యే ఇమెయిల్‌ను నమోదు చేయండి.",
    "contactDialogMessageLabel": "సందేశం",
    "contactDialogMessageDescription": "మీ సందేశాన్ని ఇక్కడ రాయండి.",
    "contactDialogCaptchaLabel": "క్యాప్చాను పరిష్కరించండి",
    "contactDialogCaptchaQuestion": "క్యాప్చా ప్రశ్న ఏమిటి?",
    "contactDialogCaptchaDescription": "ఫారమ్‌ను పంపడానికి క్యాప్చా ప్రశ్నకు సమాధానం ఇవ్వండి.",
    "contactDialogCaptchaPlaceholder": "జవాబు",
    "contactDialogSuccess": "సందేశం విజయవంతంగా పంపబడింది.",
    "contactDialogError": "క్యాప్చాను పరిష్కరించడంలో దోషం.",
    "contactDialogSubmitButtonText": "సమర్పించు",
    "contactDialogSubmitButtonAriaLabel": "సంప్రదింపు ఫారమ్‌ను సమర్పించండి",
    "contactDialogCloseButtonText": "మూసివేయండి",
    "contactDialogCloseButtonAriaLabel": "సంప్రదింపు ఫారమ్‌ను మూసివేయండి",
    "SupportOptionsNull": "ఒక ఎంపికను ఎంచుకోండి...",
    "SupportOptionsSuggestions": "సూచనలు మరియు ఫిర్యాదులు",
    "SupportOptionsTranslationErrors": "అనువాద దోషాలు",
    "SupportOptionsRecordingIssues": "రికార్డింగ్ సమస్యలు",
    "SupportOptionsQualityIssues": "వీడియో లేదా ఆడియో నాణ్యత",
    "SupportOptionsBrowserCompatibility": "బ్రౌజర్ అనుకూలత దోషాలు",
    "SupportOptionsDeviceSetup": "డివైస్ సెటప్",
    "SupportOptionsLagFreezing": "ల్యాగ్ లేదా ఫ్రీజింగ్",
    "SupportOptionsDeviceAccess": "డివైస్‌లకు నిరాకరించబడిన ప్రాప్యత",
    "SupportOptionsFeatureRequest": "కొత్త లక్షణాల కోసం అభ్యర్థనలు",
    "SupportOptionsPrivacySecurity": "గోప్యతా మరియు భద్రత గురించి ప్రశ్నలు",
    "SupportOptionsGeneralErrors": "సాధారణ దోషాలు లేదా సాంకేతిక దోషాలు",
    "terms": "నిబంధనలు",
    "privacy": "గోప్యత",
    "cookiesPolicy": "కుకీల పాలసీ",
    "legal": "చట్టపరమైన నోటీసు",
    "faq": "FAQ",
    "copyEmailTitle": "ఇమెయిల్‌ని కాపీ చేయండి",
    "copyright": "<a href='https:\/\/itechware.com' target='_blank'>iTechWare<\/a> యొక్క ప్రాజెక్ట్ | అన్ని హక్కులు రిజర్వ్ చేయబడ్డాయి... మరియు నా పిల్లులు పర్యవేక్షిస్తున్నాయి."
}